Metadata-Version: 2.3
Name: mcp-4get-fastmcp
Version: 0.1.3
Summary: An MCP server for 4get search engine
Requires-Dist: fastmcp>=2.12.3
Requires-Python: >=3.13
Project-URL: Homepage, https://github.com/fastmcp-me/mcp-4get#readme
Project-URL: Issues, https://github.com/fastmcp-me/mcp-4get/issues
Project-URL: Repository, https://github.com/fastmcp-me/mcp-4get.git
